intermol/__init__.py
intermol/atom.py
intermol/convert.py
intermol/decorators.py
intermol/exceptions.py
intermol/molecule.py
intermol/moleculetype.py
intermol/orderedset.py
intermol/system.py
intermol/utils.py
intermol/version.py
intermol/amber/__init__.py
intermol/charmm/__init__.py
intermol/desmond/__init__.py
intermol/desmond/cmap_parameters.py
intermol/desmond/desmond_parser.py
intermol/forces/__init__.py
intermol/forces/abstract_2_virtual_type.py
intermol/forces/abstract_3_virtual_type.py
intermol/forces/abstract_4_virtual_type.py
intermol/forces/abstract_angle_type.py
intermol/forces/abstract_atom_type.py
intermol/forces/abstract_bond_type.py
intermol/forces/abstract_dihedral_type.py
intermol/forces/abstract_nonbonded_type.py
intermol/forces/abstract_pair_type.py
intermol/forces/abstract_type.py
intermol/forces/atom_c_type.py
intermol/forces/atom_sigeps_type.py
intermol/forces/bending_torsion_dihedral_type.py
intermol/forces/buckingham_nonbonded_type.py
intermol/forces/connection_bond_type.py
intermol/forces/constraint.py
intermol/forces/convert_dihedrals.py
intermol/forces/cosine_angle_type.py
intermol/forces/cosine_squared_angle_type.py
intermol/forces/cross_bond_angle_angle_type.py
intermol/forces/cross_bond_bond_angle_type.py
intermol/forces/cubic_bond_type.py
intermol/forces/exclusions.py
intermol/forces/fene_bond_type.py
intermol/forces/fene_expandable_bond_type.py
intermol/forces/forcedata.py
intermol/forces/forcefunctions.py
intermol/forces/four_fdn_virtual_type.py
intermol/forces/fourier_dihedral_type.py
intermol/forces/g96_bond_type.py
intermol/forces/harmonic_angle_type.py
intermol/forces/harmonic_bond_type.py
intermol/forces/harmonic_potential_bond_type.py
intermol/forces/improper_harmonic_dihedral_type.py
intermol/forces/lj_c_nonbonded_type.py
intermol/forces/lj_c_pair_type.py
intermol/forces/lj_default_pair_type.py
intermol/forces/lj_sigeps_nonbonded_type.py
intermol/forces/lj_sigeps_pair_type.py
intermol/forces/ljq_c_pair_type.py
intermol-0.1.0.dev0.dist-info/LICENSE.md
intermol-0.1.0.dev0.dist-info/METADATA
intermol-0.1.0.dev0.dist-info/WHEEL
intermol-0.1.0.dev0.dist-info/top_level.txt
intermol-0.1.0.dev0.dist-info/RECORD
